pygamehotkeys.py
pygamehotkeys-0.0.1.dist-info/LICENSE
pygamehotkeys-0.0.1.dist-info/METADATA
pygamehotkeys-0.0.1.dist-info/WHEEL
pygamehotkeys-0.0.1.dist-info/top_level.txt
pygamehotkeys-0.0.1.dist-info/RECORD
