Metadata-Version: 2.1
Name: pygamehotkeys
Version: 0.0.1
Summary: Pygame hotkey module
Home-page: UNKNOWN
Author: Jan Dziedziak
License: UNKNOWN
Platform: UNKNOWN
Classifier: Programming Language :: Python :: 3
Classifier: License :: OSI Approved :: MIT License
Classifier: Operating System :: OS Independent
Requires-Python: >=3.6
